{
  "_type": "export",
  "__export_format": 4,
  "__export_date": "2022-07-06T12:03:37.394Z",
  "__export_source": "insomnia.desktop.app:v2022.4.2",
  "resources": [
    {
      "_id": "req_ac7f0c3686c343e09cc355ca0d30d693",
      "parentId": "fld_0dc673719865456391af9cfa854dbedf",
      "modified": 1657108680544,
      "created": 1657043578657,
      "url": "{{ _.base_url }}/{% request 'folder', '', 0 %}/{{ _.support }}/02db5ac0-0894-4c9d-8b78-e61fc52149d5",
      "name": "delete",
      "description": "",
      "method": "DELETE",
      "body": {},
      "parameters": [],
      "headers": [],
      "authentication": {},
      "metaSortKey": -1657043578657,
      "isPrivate": false,
      "settingStoreCookies": true,
      "settingSendCookies": true,
      "settingDisableRenderRequestBody": false,
      "settingEncodeUrl": true,
      "settingRebuildPath": true,
      "settingFollowRedirects": "global",
      "_type": "request"
    },
    {
      "_id": "fld_0dc673719865456391af9cfa854dbedf",
      "parentId": "wrk_700300a833a043ee8eb00c7d2e83872f",
      "modified": 1656965659616,
      "created": 1656965659616,
      "name": "clinic",
      "description": "",
      "environment": {},
      "environmentPropertyOrder": null,
      "metaSortKey": -1656965659616,
      "_type": "request_group"
    },
    {
      "_id": "wrk_700300a833a043ee8eb00c7d2e83872f",
      "parentId": null,
      "modified": 1654723859605,
      "created": 1654723859605,
      "name": "psis",
      "description": "",
      "scope": "collection",
      "_type": "workspace"
    },
    {
      "_id": "req_a3eb30f42fc742889681d6b0bddd1dc1",
      "parentId": "fld_0dc673719865456391af9cfa854dbedf",
      "modified": 1657108706423,
      "created": 1656965676597,
      "url": "{{ _.base_url }}/{% request 'folder', '', 0 %}/{{ _.support }}",
      "name": "read",
      "description": "",
      "method": "GET",
      "body": {},
      "parameters": [],
      "headers": [],
      "authentication": {},
      "metaSortKey": -1656965676597,
      "isPrivate": false,
      "settingStoreCookies": true,
      "settingSendCookies": true,
      "settingDisableRenderRequestBody": false,
      "settingEncodeUrl": true,
      "settingRebuildPath": true,
      "settingFollowRedirects": "global",
      "_type": "request"
    },
    {
      "_id": "req_698f458fffe74931b121812d0d0f19c2",
      "parentId": "fld_0dc673719865456391af9cfa854dbedf",
      "modified": 1657109002553,
      "created": 1656965740153,
      "url": "{{ _.base_url }}/{% request 'folder', '', 0 %}/{{ _.support }}",
      "name": "create",
      "description": "",
      "method": "POST",
      "body": {
        "mimeType": "application/json",
        "text": "{\n\t\"name\": \"NAME\",\n\t\"password\": \"PASSWORD\",\n\t\"email\": \"EMAIL\"\n}"
      },
      "parameters": [],
      "headers": [
        {
          "name": "Content-Type",
          "value": "application/json",
          "id": "pair_a4bb0d4f1c4a49a586275ad9c4a6d6ea"
        }
      ],
      "authentication": {},
      "metaSortKey": -1656407393455.5,
      "isPrivate": false,
      "settingStoreCookies": true,
      "settingSendCookies": true,
      "settingDisableRenderRequestBody": false,
      "settingEncodeUrl": true,
      "settingRebuildPath": true,
      "settingFollowRedirects": "global",
      "_type": "request"
    },
    {
      "_id": "env_221a7fa111ada18e40dfea03e4644ba670ce780f",
      "parentId": "wrk_700300a833a043ee8eb00c7d2e83872f",
      "modified": 1654723888156,
      "created": 1654723859622,
      "name": "Base Environment",
      "data": {},
      "dataPropertyOrder": {},
      "color": null,
      "isPrivate": false,
      "metaSortKey": 1654723859622,
      "_type": "environment"
    },
    {
      "_id": "jar_221a7fa111ada18e40dfea03e4644ba670ce780f",
      "parentId": "wrk_700300a833a043ee8eb00c7d2e83872f",
      "modified": 1654723859625,
      "created": 1654723859625,
      "name": "Default Jar",
      "cookies": [],
      "_type": "cookie_jar"
    },
    {
      "_id": "spc_0b6ff59be397401e96ef0fe40cb94113",
      "parentId": "wrk_700300a833a043ee8eb00c7d2e83872f",
      "modified": 1654723859613,
      "created": 1654723859613,
      "fileName": "psis",
      "contents": "",
      "contentType": "yaml",
      "_type": "api_spec"
    },
    {
      "_id": "env_bf434227e85e4802946f974da7327772",
      "parentId": "env_221a7fa111ada18e40dfea03e4644ba670ce780f",
      "modified": 1657108972729,
      "created": 1654723872664,
      "name": "dev",
      "data": {
        "base_url": "http://localhost:3333/api",
        "support": "e1cab50c402d99685c069ab7e997ca657e78a518"
      },
      "dataPropertyOrder": {
        "&": [
          "base_url",
          "support"
        ]
      },
      "color": "#10e529",
      "isPrivate": false,
      "metaSortKey": 1654723872664,
      "_type": "environment"
    },
    {
      "_id": "env_cd2af759256b4b209d7b6527817ff98f",
      "parentId": "env_221a7fa111ada18e40dfea03e4644ba670ce780f",
      "modified": 1657108962905,
      "created": 1654723874269,
      "name": "homolog",
      "data": {
        "base_url": "https://psis-api.herokuapp.com/api",
        "support": ""
      },
      "dataPropertyOrder": {
        "&": [
          "base_url",
          "support"
        ]
      },
      "color": "#f00f0f",
      "isPrivate": false,
      "metaSortKey": 1654723874269,
      "_type": "environment"
    }
  ]
}